indiek/mockdb/__init__.py
indiek/mockdb/items.py
indiek/mockdb/persistence.py
indiek_mockdb-0.1.4.dist-info/LICENSE
indiek_mockdb-0.1.4.dist-info/METADATA
indiek_mockdb-0.1.4.dist-info/WHEEL
indiek_mockdb-0.1.4.dist-info/top_level.txt
indiek_mockdb-0.1.4.dist-info/RECORD
